{"accent_phrases": [{"moras": [{"text": "\u30b8\u30e5", "consonant": "j", "consonant_length": 0.11660268157720566, "vowel": "u", "vowel_length": 0.09805876761674881, "pitch": 5.557598114013672}, {"text": "\u30a6", "consonant": null, "consonant_length": null, "vowel": "u", "vowel_length": 0.08764520287513733, "pitch": 5.915345191955566}], "accent": 2, "pause_mora": null, "is_interrogative": false}, {"moras": [{"text": "\u30cb", "consonant": "n", "consonant_length": 0.06436396390199661, "vowel": "i", "vowel_length": 0.09344233572483063, "pitch": 6.079854488372803}, {"text": "\u30b8", "consonant": "j", "consonant_length": 0.07781083136796951, "vowel": "i", "vowel_length": 0.06044883280992508, "pitch": 6.086609840393066}, {"text": "\u30c7", "consonant": "d", "consonant_length": 0.05530247837305069, "vowel": "e", "vowel_length": 0.12975503504276276, "pitch": 5.972351551055908}, {"text": "\u30b9", "consonant": "s", "consonant_length": 0.08062320947647095, "vowel": "U", "vowel_length": 0.1007721796631813, "pitch": 0.0}], "accent": 1, "pause_mora": null, "is_interrogative": false}], "speedScale": 1.0, "pitchScale": 0.0, "intonationScale": 1.0, "volumeScale": 1.0, "prePhonemeLength": 0.1, "postPhonemeLength": 0.1, "outputSamplingRate": 24000, "outputStereo": false, "kana": "\u30b8\u30e5\u30a6'/\u30cb'\u30b8\u30c7_\u30b9"}
