{"accent_phrases": [{"moras": [{"text": "\u30b8\u30e5", "consonant": "j", "consonant_length": 0.11888343840837479, "vowel": "u", "vowel_length": 0.08935099095106125, "pitch": 5.520204544067383}, {"text": "\u30a6", "consonant": null, "consonant_length": null, "vowel": "u", "vowel_length": 0.0878990963101387, "pitch": 5.840595245361328}], "accent": 2, "pause_mora": null, "is_interrogative": false}, {"moras": [{"text": "\u30b5", "consonant": "s", "consonant_length": 0.09037675708532333, "vowel": "a", "vowel_length": 0.14031647145748138, "pitch": 6.045548915863037}, {"text": "\u30f3", "consonant": null, "consonant_length": null, "vowel": "N", "vowel_length": 0.07472547143697739, "pitch": 6.111726760864258}, {"text": "\u30b8", "consonant": "j", "consonant_length": 0.04646216332912445, "vowel": "i", "vowel_length": 0.06089784950017929, "pitch": 6.058176040649414}, {"text": "\u30c7", "consonant": "d", "consonant_length": 0.05234961956739426, "vowel": "e", "vowel_length": 0.1270318329334259, "pitch": 5.99175500869751}, {"text": "\u30b9", "consonant": "s", "consonant_length": 0.08282189071178436, "vowel": "U", "vowel_length": 0.10027190297842026, "pitch": 0.0}], "accent": 2, "pause_mora": null, "is_interrogative": false}], "speedScale": 1.0, "pitchScale": 0.0, "intonationScale": 1.0, "volumeScale": 1.0, "prePhonemeLength": 0.1, "postPhonemeLength": 0.1, "outputSamplingRate": 24000, "outputStereo": false, "kana": "\u30b8\u30e5\u30a6'/\u30b5\u30f3'\u30b8\u30c7_\u30b9"}
